[{"name":"Abundant Growth","id":"1a05b2f6-a6b3-4e30-904b-0dc85d124ef8","ci":["G"],"commander":false,"legalities":["modern","legacy","pauper","vintage","commander","oathbreaker","paupercommander","duel"]},{"name":"Acidic Slime","id":"2a6d791f-11c1-44ce-8084-591250b9f802","ci":["G"],"commander":false,"legalities":["modern","legacy","vintage","penny","commander","oathbreaker","duel","predh"]},{"name":"Angelic Gift","id":"5a2122c0-5fb4-4767-b969-c61bd959d604","ci":["W"],"commander":false,"legalities":["historic","gladiator","pioneer","explorer","modern","legacy","pauper","vintage","penny","commander","oathbreaker","historicbrawl","paupercommander","duel"]},{"name":"Angel of Finality","id":"c3dc3acf-ec09-4c24-ade6-6f4dd30bd0a8","ci":["W"],"commander":false,"legalities":["legacy","vintage","commander","oathbreaker","duel"]},{"name":"Anger","id":"0c7ce363-3f57-49ed-b89a-f12bb5227ab4","ci":["R"],"commander":false,"legalities":["legacy","vintage","commander","oathbreaker","duel","premodern","predh"]},{"name":"Apex of Power","id":"dc922e89-c816-476a-82c3-3c6b9fd196a9","ci":["R"],"commander":false,"legalities":["historic","gladiator","pioneer","explorer","modern","legacy","vintage","penny","commander","oathbreaker","historicbrawl","duel"]},{"name":"Arcane Endeavor","id":"7886d4e9-003c-4978-a48d-4743fbc38985","ci":["U"],"commander":false,"legalities":["legacy","vintage","commander","oathbreaker","duel"]},{"name":"Arcane Sanctum","id":"48d87619-6a6d-42ba-8a69-910d3cc7aede","ci":[],"commander":false,"legalities":["modern","legacy","vintage","penny","commander","oathbreaker","duel","predh"]},{"name":"Arcane Signet","id":"552be01e-cd54-46ba-b38a-96883a48d985","ci":[],"commander":false,"legalities":["historic","gladiator","pioneer","explorer","modern","legacy","pauper","vintage","commander","oathbreaker","brawl","historicbrawl","alchemy","paupercommander","duel"]},{"name":"Argentum Armor","id":"fb1b7468-85f9-472e-9f7c-b268f84aea1c","ci":[],"commander":false,"legalities":["modern","legacy","vintage","penny","commander","oathbreaker","duel","predh"]},{"name":"Ashen Rider","id":"dae91853-6487-46db-8f09-8aa4c2e19e5f","ci":["B","W"],"commander":false,"legalities":["pioneer","modern","legacy","vintage","commander","oathbreaker","duel"]},{"name":"Atarka, World Render","id":"35ad1ce5-6054-4f0c-8fbe-636be576d408","ci":["G","R"],"commander":true,"legalities":["pioneer","modern","legacy","vintage","penny","commander","oathbreaker","duel"]},{"name":"Azorius Chancery","id":"cdcce65a-5645-4444-9f49-0270fab0e440","ci":[],"commander":false,"legalities":["modern","legacy","pauper","vintage","penny","commander","oathbreaker","paupercommander","duel","predh"]},{"name":"Bag of Devouring","id":"d183e52b-432d-4b4d-803c-33f7a5f178f1","ci":["B"],"commander":false,"legalities":["legacy","vintage","commander","oathbreaker","duel"]},{"name":"Bag of Tricks","id":"f0b22a3e-90b0-4dde-8a63-789bab92ba01","ci":["G"],"commander":false,"legalities":["legacy","vintage","commander","oathbreaker","duel"]},{"name":"Baleful Strix","id":"3e417331-84ec-4513-8022-e93ffc260a38","ci":["B","U"],"commander":false,"legalities":["legacy","vintage","commander","oathbreaker","duel"]},{"name":"Bant Charm","id":"7bb17888-f298-438d-aab0-3d28111daa3f","ci":["G","U","W"],"commander":false,"legalities":["modern","legacy","vintage","penny","commander","oathbreaker","duel","predh"]},{"name":"Bant Panorama","id":"c1b0eb8f-f91e-43d0-9c16-2f330612550a","ci":[],"commander":false,"legalities":["modern","legacy","pauper","vintage","penny","commander","oathbreaker","paupercommander","duel","predh"]},{"name":"Basilisk Collar","id":"0d85fb76-2ae9-425b-9c5e-2c63471c9599","ci":[],"commander":false,"legalities":["historic","gladiator","modern","legacy","vintage","commander","oathbreaker","historicbrawl","alchemy","duel","predh"]},{"name":"Beast Within","id":"6dc4dfa3-527f-4401-bc76-32d81e9f6ef1","ci":["G"],"commander":false,"legalities":["modern","legacy","vintage","commander","oathbreaker","duel","predh"]},{"name":"Bedevil","id":"ffd34d49-9c77-499d-a9ad-a491f5d169d0","ci":["B","R"],"commander":false,"legalities":["historic","gladiator","pioneer","explorer","modern","legacy","vintage","commander","oathbreaker","historicbrawl","duel"]},{"name":"Behemoth Sledge","id":"179461b8-0a6b-48c5-9d1f-db8bcfecc6f9","ci":["G","W"],"commander":false,"legalities":["modern","legacy","vintage","penny","commander","oathbreaker","duel","predh"]},{"name":"Belt of Giant Strength","id":"4ef2b9aa-4f7c-4640-bb34-9775e1be0935","ci":["G"],"commander":false,"legalities":["historic","gladiator","legacy","vintage","commander","oathbreaker","historicbrawl","alchemy","duel"]},{"name":"Berserker's Frenzy","id":"36b50ed5-321f-4840-82d7-54fec200984d","ci":["R"],"commander":false,"legalities":["legacy","vintage","commander","oathbreaker","duel"]},{"name":"Bituminous Blast","id":"af8613ee-4b67-49b8-920b-3b5a25897f64","ci":["B","R"],"commander":false,"legalities":["modern","legacy","vintage","penny","commander","oathbreaker","duel","predh"]},{"name":"Bogardan Hellkite","id":"22dd2242-2fd8-4752-886c-fc6dbabcf89a","ci":["R"],"commander":false,"legalities":["modern","legacy","vintage","penny","commander","oathbreaker","duel","predh"]},{"name":"Bojuka Bog","id":"6e1d1e83-c34a-46af-8aec-ff698446099f","ci":[],"commander":false,"legalities":["historic","gladiator","modern","legacy","pauper","vintage","commander","oathbreaker","historicbrawl","paupercommander","duel","predh"]},{"name":"Brainstorm","id":"48070245-1370-4cf1-be15-d4e8a8b92ba8","ci":["U"],"commander":false,"legalities":["gladiator","legacy","pauper","commander","oathbreaker","historicbrawl","paupercommander","duel","predh"]},{"name":"Bucknard's Everfull Purse","id":"57073533-dcd8-4a86-9aa8-d7205d3799e1","ci":[],"commander":false,"legalities":["legacy","vintage","commander","oathbreaker","duel"]},{"name":"Burnished Hart","id":"0f22bcce-4f9a-4e82-a684-63ab9cce90ed","ci":[],"commander":false,"legalities":["historic","gladiator","pioneer","explorer","modern","legacy","vintage","penny","commander","oathbreaker","historicbrawl","duel"]},{"name":"Canopy Vista","id":"602f0a45-1fe8-4557-bcde-40932b6e7065","ci":[],"commander":false,"legalities":["pioneer","modern","legacy","vintage","commander","oathbreaker","duel"]},{"name":"Cataclysmic Gearhulk","id":"92aaf9d2-cb83-40be-b39c-05cb3721776e","ci":["W"],"commander":false,"legalities":["historic","gladiator","pioneer","explorer","modern","legacy","vintage","penny","commander","oathbreaker","historicbrawl","duel"]},{"name":"Catti-brie of Mithral Hall","id":"d3626ede-6c69-4fd5-8de1-cf85f50cd435","ci":["G","W"],"commander":true,"legalities":["historic","gladiator","legacy","vintage","commander","oathbreaker","historicbrawl","alchemy","duel"]},{"name":"Chain Reaction","id":"e631b484-37a2-4532-b4da-f24ee03152f6","ci":["R"],"commander":false,"legalities":["modern","legacy","vintage","penny","commander","oathbreaker","duel","predh"]},{"name":"Chameleon Colossus","id":"15401ca4-f6cd-400e-8e5e-ea47493b56a4","ci":["G"],"commander":false,"legalities":["modern","legacy","vintage","penny","commander","oathbreaker","duel","predh"]},{"name":"Champion of Wits","id":"cce2fce1-8172-43ed-937d-a543a474ef46","ci":["U"],"commander":false,"legalities":["historic","gladiator","pioneer","explorer","modern","legacy","vintage","penny","commander","oathbreaker","historicbrawl","duel"]},{"name":"Chaos Dragon","id":"27aee582-0d32-428c-8ffa-4122e92a810d","ci":["R"],"commander":false,"legalities":["legacy","vintage","commander","oathbreaker","duel"]},{"name":"Chaos Wand","id":"4d50a9d5-4eb7-4eb9-bdf5-5a7703b4c6b6","ci":[],"commander":false,"legalities":["historic","gladiator","pioneer","explorer","modern","legacy","vintage","penny","commander","oathbreaker","historicbrawl","duel"]},{"name":"Chaos Warp","id":"63cf7776-1b1a-4539-8f53-b8c30addc7de","ci":["R"],"commander":false,"legalities":["historic","gladiator","legacy","vintage","commander","oathbreaker","historicbrawl","duel"]},{"name":"Chittering Witch","id":"b57c76be-082e-4552-9830-403a98992619","ci":["B"],"commander":false,"legalities":["historic","gladiator","pioneer","explorer","modern","legacy","vintage","penny","commander","oathbreaker","historicbrawl","duel"]},{"name":"Choked Estuary","id":"5573b816-97d0-46c1-8438-f5740fa4759a","ci":[],"commander":false,"legalities":["historic","gladiator","pioneer","explorer","modern","legacy","vintage","commander","oathbreaker","historicbrawl","duel"]},{"name":"Cinder Glade","id":"e755e021-b725-4a5f-bfd7-7406fa945111","ci":[],"commander":false,"legalities":["pioneer","modern","legacy","vintage","commander","oathbreaker","duel"]},{"name":"Clay Golem","id":"3a949c88-07bb-4526-9460-9324574cc466","ci":[],"commander":false,"legalities":["legacy","vintage","commander","oathbreaker","duel"]},{"name":"Cloudblazer","id":"2f64ae7d-0bd0-41f8-8f7d-64db4bd2a10b","ci":["U","W"],"commander":false,"legalities":["historic","gladiator","pioneer","explorer","modern","legacy","vintage","penny","commander","oathbreaker","historicbrawl","duel"]},{"name":"Cold-Eyed Selkie","id":"b85d0834-065b-45e1-b739-08d5a5a4db2a","ci":["G","U"],"commander":false,"legalities":["modern","legacy","vintage","penny","commander","oathbreaker","duel","predh"]},{"name":"Colossal Majesty","id":"5db24df1-580f-4ff5-91a7-9a64a8352883","ci":["G"],"commander":false,"legalities":["historic","gladiator","pioneer","explorer","modern","legacy","vintage","commander","oathbreaker","historicbrawl","alchemy","duel"]},{"name":"Colossus Hammer","id":"897a134e-7e61-4fe1-bbae-23ef1fe5c0cf","ci":[],"commander":false,"legalities":["historic","gladiator","pioneer","explorer","modern","legacy","vintage","commander","oathbreaker","historicbrawl","duel"]},{"name":"Commander's Sphere","id":"08e8b5a4-ea2b-42fe-880c-f6a4f5456b66","ci":[],"commander":false,"legalities":["legacy","pauper","vintage","commander","oathbreaker","paupercommander","duel"]},{"name":"Command Tower","id":"3edb78c2-0a3c-46e1-a7ff-97dbd8402495","ci":[],"commander":false,"legalities":["historic","gladiator","pioneer","explorer","modern","legacy","pauper","vintage","commander","oathbreaker","brawl","historicbrawl","alchemy","paupercommander","duel"]},{"name":"Commune with Lava","id":"862771b6-8e82-45b7-922f-4f40322a607e","ci":["R"],"commander":false,"legalities":["pioneer","modern","legacy","vintage","penny","commander","oathbreaker","duel"]},{"name":"Component Pouch","id":"8aa4eacb-48d8-49a1-90dd-042f3f1f75bb","ci":[],"commander":false,"legalities":["legacy","vintage","commander","oathbreaker","duel"]},{"name":"Consuming Vapors","id":"7b6e74a3-f390-4ad2-93de-930af0e5585c","ci":["B"],"commander":false,"legalities":["modern","legacy","vintage","penny","commander","oathbreaker","duel","predh"]},{"name":"Crucible of the Spirit Dragon","id":"257a5ae9-f754-4c45-a47d-5196f1b625b7","ci":[],"commander":false,"legalities":["pioneer","modern","legacy","vintage","penny","commander","oathbreaker","duel"]},{"name":"Cultivate","id":"2c7b84c8-b79d-4d05-8d2e-23657bd6ca7c","ci":["G"],"commander":false,"legalities":["historic","gladiator","pioneer","explorer","modern","legacy","pauper","vintage","penny","commander","oathbreaker","historicbrawl","paupercommander","duel","predh"]},{"name":"Curator of Mysteries","id":"98b959ad-8920-4b28-a954-f733bf36bde8","ci":["U"],"commander":false,"legalities":["historic","gladiator","pioneer","explorer","modern","legacy","vintage","penny","commander","oathbreaker","historicbrawl","duel"]},{"name":"Curse of Verbosity","id":"3054eba1-238f-4328-8e9f-5148b5c37aac","ci":["U"],"commander":false,"legalities":["legacy","vintage","commander","oathbreaker","duel"]},{"name":"Danse Macabre","id":"5151b81b-6d10-40de-9e65-89923e4c03d9","ci":["B"],"commander":false,"legalities":["legacy","vintage","commander","oathbreaker","duel"]},{"name":"Dark-Dweller Oracle","id":"4055e8a0-eb0d-4754-b07a-399cb914917c","ci":["R"],"commander":false,"legalities":["historic","gladiator","pioneer","explorer","modern","legacy","pauper","vintage","penny","commander","oathbreaker","historicbrawl","paupercommander","duel"]},{"name":"Darkwater Catacombs","id":"5db9d318-7d50-47fb-9979-abd43641f887","ci":[],"commander":false,"legalities":["legacy","vintage","commander","oathbreaker","duel","premodern","predh"]},{"name":"Dead Man's Chest","id":"7a0b60a2-50de-4328-85dc-040bf8a4dac9","ci":["B"],"commander":false,"legalities":["historic","gladiator","pioneer","explorer","modern","legacy","vintage","penny","commander","oathbreaker","historicbrawl","duel"]},{"name":"Death Tyrant","id":"b9e508e9-c190-4db2-a278-9dbb09515ae2","ci":["B"],"commander":false,"legalities":["legacy","vintage","commander","oathbreaker","duel"]},{"name":"Decree of Savagery","id":"ec6d7db1-eeb2-4e9e-9a4f-488595bbcf1c","ci":["G"],"commander":false,"legalities":["legacy","vintage","penny","commander","oathbreaker","duel","premodern","predh"]},{"name":"Demanding Dragon","id":"4d8a5bab-813a-488a-ab65-3286582ef595","ci":["R"],"commander":false,"legalities":["historic","gladiator","pioneer","explorer","modern","legacy","vintage","penny","commander","oathbreaker","historicbrawl","duel"]},{"name":"Desert","id":"c74e13eb-6f82-4db1-9d0d-8310f48d9f6d","ci":[],"commander":false,"legalities":["modern","legacy","pauper","vintage","commander","oathbreaker","paupercommander","duel","predh"]},{"name":"Despark","id":"970a63b9-c835-43f4-ba3e-f6b919a3f2d3","ci":["B","W"],"commander":false,"legalities":["historic","gladiator","pioneer","explorer","modern","legacy","vintage","commander","oathbreaker","historicbrawl","duel"]},{"name":"Dimir Aqueduct","id":"b1b2af4a-2e26-4c66-b514-f9c3a96b0943","ci":[],"commander":false,"legalities":["modern","legacy","pauper","vintage","penny","commander","oathbreaker","paupercommander","duel","predh"]},{"name":"Dire Fleet Daredevil","id":"28c3c7d7-bf25-4dd7-8fbf-4c8ae6603dd1","ci":["R"],"commander":false,"legalities":["historic","gladiator","pioneer","explorer","modern","legacy","vintage","penny","commander","oathbreaker","historicbrawl","duel"]},{"name":"Disrupt Decorum","id":"bc91f0d5-6d50-4f71-a229-286364984e61","ci":["R"],"commander":false,"legalities":["legacy","vintage","commander","oathbreaker","duel"]},{"name":"Diviner's Portent","id":"725b8b21-64f0-4449-ad65-c8144e64836f","ci":["U"],"commander":false,"legalities":["legacy","vintage","commander","oathbreaker","duel"]},{"name":"Doomed Necromancer","id":"2d3225e8-9902-4826-9cb3-68ecfaebb1e9","ci":["B"],"commander":false,"legalities":["historic","gladiator","modern","legacy","vintage","penny","commander","oathbreaker","historicbrawl","duel","premodern","predh"]},{"name":"Dragonborn Champion","id":"9f6e43a7-84b9-4e89-bfe1-442d08df34d8","ci":["G","R"],"commander":false,"legalities":["legacy","vintage","commander","oathbreaker","duel"]},{"name":"Dragonlord's Servant","id":"03a4e477-22d4-49b4-8e36-160bb4810e2b","ci":["R"],"commander":false,"legalities":["historic","gladiator","pioneer","explorer","modern","legacy","pauper","vintage","penny","commander","oathbreaker","historicbrawl","paupercommander","duel"]},{"name":"Dragonmaster Outcast","id":"2dfc4cfe-d1f7-43e4-a543-35c050d01a8f","ci":["R"],"commander":false,"legalities":["historic","gladiator","pioneer","explorer","modern","legacy","vintage","penny","commander","oathbreaker","historicbrawl","duel","predh"]},{"name":"Dragon's Hoard","id":"8845aa0f-f52d-4d9e-a4e2-1cadad84f948","ci":[],"commander":false,"legalities":["historic","gladiator","pioneer","explorer","modern","legacy","vintage","penny","commander","oathbreaker","historicbrawl","duel"]},{"name":"Dragonspeaker Shaman","id":"7b0a2799-197e-4d61-ab23-67d974458a05","ci":["R"],"commander":false,"legalities":["historic","gladiator","legacy","vintage","commander","oathbreaker","historicbrawl","duel","premodern","predh"]},{"name":"Dream Pillager","id":"f872b587-0afe-4aeb-b0bf-43ec692d495a","ci":["R"],"commander":false,"legalities":["legacy","vintage","commander","oathbreaker","duel"]},{"name":"Druid of Purification","id":"096c2b28-3e29-4c27-998d-51bff0ba96c5","ci":["G"],"commander":false,"legalities":["legacy","vintage","commander","oathbreaker","duel"]},{"name":"Ebony Fly","id":"7f11245d-9e80-42b0-b371-21e990a2e6ef","ci":[],"commander":false,"legalities":["legacy","vintage","commander","oathbreaker","duel"]},{"name":"Eel Umbra","id":"2c60fcaa-ef75-42e4-b255-066e345e45b8","ci":["U"],"commander":false,"legalities":["modern","legacy","pauper","vintage","penny","commander","oathbreaker","paupercommander","duel","predh"]},{"name":"Esper Panorama","id":"73fbd385-c5c4-45da-8a6d-9597bf904294","ci":[],"commander":false,"legalities":["modern","legacy","pauper","vintage","penny","commander","oathbreaker","paupercommander","duel","predh"]},{"name":"Etali, Primal Storm","id":"5ed1070d-fc21-4f4c-8e6e-5e4a2e6e2dce","ci":["R"],"commander":true,"legalities":["historic","gladiator","pioneer","explorer","modern","legacy","vintage","penny","commander","oathbreaker","historicbrawl","duel"]},{"name":"Eternal Dragon","id":"0f57fc0c-cab1-4eb0-a58a-0c7a762f1572","ci":["W"],"commander":false,"legalities":["legacy","vintage","penny","commander","oathbreaker","duel","premodern","predh"]},{"name":"Exotic Orchard","id":"c5a8de0f-726a-4ea3-9215-5188f7181951","ci":[],"commander":false,"legalities":["modern","legacy","vintage","commander","oathbreaker","duel","predh"]},{"name":"Explore","id":"59c33065-1bdd-4257-9e74-1f2aacf063c5","ci":["G"],"commander":false,"legalities":["historic","gladiator","modern","legacy","pauper","vintage","commander","oathbreaker","historicbrawl","paupercommander","duel","predh"]},{"name":"Explorer's Scope","id":"1ef03100-f095-43e4-a697-2f473779b5a9","ci":[],"commander":false,"legalities":["modern","legacy","pauper","vintage","penny","commander","oathbreaker","paupercommander","duel","predh"]},{"name":"Extract Brain","id":"344e9383-5481-4abe-a59d-3a0145b7cca2","ci":["B","U"],"commander":false,"legalities":["legacy","vintage","commander","oathbreaker","duel"]},{"name":"Fellwar Stone","id":"07be53ef-c7b7-44fe-9754-b76871c6b55f","ci":[],"commander":false,"legalities":["modern","legacy","pauper","vintage","commander","oathbreaker","paupercommander","duel","premodern","predh"]},{"name":"Fertile Ground","id":"0ade2db8-482e-42b0-939c-492dfbbe3b68","ci":["G"],"commander":false,"legalities":["modern","legacy","pauper","vintage","penny","commander","oathbreaker","paupercommander","duel","premodern","predh"]},{"name":"Fevered Suspicion","id":"82c35cce-5b13-4870-8710-1b05af2c5c40","ci":["B","R"],"commander":false,"legalities":["legacy","vintage","commander","oathbreaker","duel"]},{"name":"Fey Steed","id":"ce2bfc76-04b4-46ed-b495-33221256afbb","ci":["W"],"commander":false,"legalities":["legacy","vintage","commander","oathbreaker","duel"]},{"name":"Fiendlash","id":"9cbc0e7e-b478-431e-abaf-ce7113057730","ci":["R"],"commander":false,"legalities":["historic","gladiator","legacy","vintage","commander","oathbreaker","historicbrawl","alchemy","duel"]},{"name":"Fiend of the Shadows","id":"373f24b1-e763-475c-9760-aefae4be3ea0","ci":["B"],"commander":false,"legalities":["modern","legacy","vintage","penny","commander","oathbreaker","duel"]},{"name":"Fleecemane Lion","id":"ef4e1c37-d520-4025-bd56-15ec452f6842","ci":["G","W"],"commander":false,"legalities":["pioneer","modern","legacy","vintage","penny","commander","oathbreaker","duel"]},{"name":"Flood Plain","id":"84503325-1e80-4f29-819d-be1d5eb05bd7","ci":[],"commander":false,"legalities":["legacy","vintage","penny","commander","oathbreaker","duel","premodern","predh"]},{"name":"Forbidden Alchemy","id":"079cfabe-f072-42c7-82ee-4fcebdc8529c","ci":["U"],"commander":false,"legalities":["historic","gladiator","modern","legacy","pauper","vintage","penny","commander","oathbreaker","historicbrawl","paupercommander","duel"]},{"name":"Foreboding Ruins","id":"1ce2c480-6a5a-4e7c-b3d7-7dc9cc589912","ci":[],"commander":false,"legalities":["historic","gladiator","pioneer","explorer","modern","legacy","vintage","penny","commander","oathbreaker","historicbrawl","duel"]},{"name":"Fortified Village","id":"8788797a-724e-49c7-91b2-67fbb0660fda","ci":[],"commander":false,"legalities":["historic","gladiator","pioneer","explorer","modern","legacy","vintage","penny","commander","oathbreaker","historicbrawl","duel"]},{"name":"Galea, Kindler of Hope","id":"1efbea01-c6a1-4380-a14f-6206c7895e48","ci":["G","U","W"],"commander":true,"legalities":["legacy","vintage","commander","oathbreaker","duel"]},{"name":"Game Trail","id":"77b532ea-f170-4b04-970c-2128978941a4","ci":[],"commander":false,"legalities":["historic","gladiator","pioneer","explorer","modern","legacy","vintage","penny","commander","oathbreaker","historicbrawl","duel"]},{"name":"Garruk's Uprising","id":"7de1015f-8371-4fa6-817f-d10d11d50093","ci":["G"],"commander":false,"legalities":["historic","gladiator","pioneer","explorer","modern","legacy","vintage","commander","oathbreaker","historicbrawl","duel"]},{"name":"Geier Reach Sanitarium","id":"cdb751d3-580f-44dd-a1e2-0f1240f2b891","ci":[],"commander":false,"legalities":["historic","gladiator","pioneer","explorer","modern","legacy","vintage","penny","commander","oathbreaker","historicbrawl","duel"]},{"name":"Gonti, Lord of Luxury","id":"85ea4d39-14cd-4d11-b021-c09556f1e0ee","ci":["B"],"commander":true,"legalities":["historic","gladiator","pioneer","explorer","modern","legacy","vintage","penny","commander","oathbreaker","historicbrawl","duel"]},{"name":"Grasslands","id":"66de370b-3be5-420b-b619-2709565c7206","ci":[],"commander":false,"legalities":["legacy","vintage","penny","commander","oathbreaker","duel","premodern","predh"]},{"name":"Gratuitous Violence","id":"73a5760c-e412-4bb4-b176-cfd0e8fc8f95","ci":["R"],"commander":false,"legalities":["legacy","vintage","commander","oathbreaker","duel","premodern","predh"]},{"name":"Grave Endeavor","id":"1ef4b0fb-d4a5-43ce-a079-10d346e194d5","ci":["B"],"commander":false,"legalities":["legacy","vintage","commander","oathbreaker","duel"]},{"name":"Greater Good","id":"4c73ca01-d8ea-4cd2-af60-b260030967b2","ci":["G"],"commander":false,"legalities":["modern","legacy","vintage","penny","commander","oathbreaker","duel","premodern","predh"]},{"name":"Grim Hireling","id":"08c6872d-4cb5-4a59-b1dd-38c107906660","ci":["B"],"commander":false,"legalities":["historic","gladiator","legacy","vintage","commander","oathbreaker","historicbrawl","alchemy","duel"]},{"name":"Gruul Signet","id":"72e34c48-8721-4603-a2de-2bbf17ceee11","ci":[],"commander":false,"legalities":["modern","legacy","pauper","vintage","penny","commander","oathbreaker","paupercommander","duel","predh"]},{"name":"Gruul Turf","id":"c3543b96-43de-4abc-a1be-39a5224778f7","ci":[],"commander":false,"legalities":["modern","legacy","pauper","vintage","penny","commander","oathbreaker","paupercommander","duel","predh"]},{"name":"Gryff's Boon","id":"e66702a8-b48d-4c80-9998-a14b094dcf88","ci":["W"],"commander":false,"legalities":["historic","gladiator","pioneer","explorer","modern","legacy","vintage","penny","commander","oathbreaker","historicbrawl","duel"]},{"name":"Halimar Depths","id":"36a04300-764b-4faf-ad46-7516360c9516","ci":[],"commander":false,"legalities":["modern","legacy","pauper","vintage","penny","commander","oathbreaker","paupercommander","duel","predh"]},{"name":"Haven of the Spirit Dragon","id":"637ea3f0-d3ec-4cd4-8725-b845c50a6b96","ci":[],"commander":false,"legalities":["pioneer","modern","legacy","vintage","penny","commander","oathbreaker","duel"]},{"name":"Heirloom Blade","id":"7fcda1a2-87e0-4b9e-acb9-0bab521792fe","ci":[],"commander":false,"legalities":["legacy","vintage","commander","oathbreaker","duel"]},{"name":"Hellish Rebuke","id":"b4b558cf-8754-4c4f-87f1-8e6d84b93658","ci":["B"],"commander":false,"legalities":["legacy","vintage","commander","oathbreaker","duel"]},{"name":"Heroic Intervention","id":"c5e72882-dbf8-42d2-9a98-31f2f71e2ed9","ci":["G"],"commander":false,"legalities":["historic","gladiator","pioneer","explorer","modern","legacy","vintage","commander","oathbreaker","historicbrawl","duel"]},{"name":"Hex","id":"c5c84b30-4b52-43b4-a17b-120fc62a4dd2","ci":["B"],"commander":false,"legalities":["modern","legacy","vintage","penny","commander","oathbreaker","duel","predh"]},{"name":"High Market","id":"9d56844f-ee3b-4161-85d2-18b872a9b465","ci":[],"commander":false,"legalities":["legacy","vintage","commander","oathbreaker","duel","premodern","predh"]},{"name":"Hoard-Smelter Dragon","id":"2f4c5867-73c4-4e10-bbf5-6a69df879547","ci":["R"],"commander":false,"legalities":["modern","legacy","vintage","penny","commander","oathbreaker","duel","predh"]},{"name":"Holy Avenger","id":"4d64d158-3477-4530-9596-2d4e4eceb11a","ci":["W"],"commander":false,"legalities":["legacy","vintage","commander","oathbreaker","duel"]},{"name":"Hostage Taker","id":"c8b103d1-d5f5-4dde-9474-e899d1e51eac","ci":["B","U"],"commander":false,"legalities":["historic","gladiator","pioneer","explorer","modern","legacy","vintage","penny","commander","oathbreaker","historicbrawl","duel"]},{"name":"Hurl Through Hell","id":"47a3321c-28ed-4cd7-84d8-c8cecc09348b","ci":["B","R"],"commander":false,"legalities":["legacy","vintage","commander","oathbreaker","duel"]},{"name":"Ignite the Future","id":"6fdc6fcf-2fd7-4751-b352-0992bc880132","ci":["R"],"commander":false,"legalities":["legacy","vintage","commander","oathbreaker","duel"]},{"name":"Immovable Rod","id":"214c87be-7ce3-48a0-b2eb-26eff75636c9","ci":["W"],"commander":false,"legalities":["legacy","vintage","commander","oathbreaker","duel"]},{"name":"Imprisoned in the Moon","id":"1d916675-1e7e-477f-bbb5-bd54fdfd8159","ci":["U"],"commander":false,"legalities":["historic","gladiator","pioneer","explorer","modern","legacy","vintage","penny","commander","oathbreaker","historicbrawl","duel"]},{"name":"Indomitable Might","id":"063b156b-7e05-4b49-a40a-54d713004ebf","ci":["G"],"commander":false,"legalities":["legacy","vintage","commander","oathbreaker","duel"]},{"name":"Izzet Chemister","id":"4073a490-1977-41c0-9e0d-953235b7f2b0","ci":["R"],"commander":false,"legalities":["legacy","vintage","penny","commander","oathbreaker","duel"]},{"name":"Karazikar, the Eye Tyrant","id":"da46b47b-0156-4a01-b4b1-28526a6826f4","ci":["B","R"],"commander":true,"legalities":["legacy","vintage","commander","oathbreaker","duel"]},{"name":"Karmic Guide","id":"c48e3d51-1c63-4b39-97df-92c260311dad","ci":["W"],"commander":false,"legalities":["modern","legacy","vintage","penny","commander","oathbreaker","duel","premodern","predh"]},{"name":"Kenrith's Transformation","id":"44d60a41-3f5e-4559-b18c-22c0fe15235e","ci":["G"],"commander":false,"legalities":["historic","gladiator","pioneer","explorer","modern","legacy","vintage","commander","oathbreaker","historicbrawl","duel"]},{"name":"Kindred Summons","id":"54c0cc74-0a5c-40ee-961b-ade71719937a","ci":["G"],"commander":false,"legalities":["legacy","vintage","commander","oathbreaker","duel"]},{"name":"Klauth's Will","id":"761e1f77-5231-4008-829f-99650b429fb3","ci":["G","R"],"commander":false,"legalities":["legacy","vintage","commander","oathbreaker","duel"]},{"name":"Klauth, Unrivaled Ancient","id":"7f5cf828-17b2-4105-9a9a-ee0ab720c2ee","ci":["G","R"],"commander":true,"legalities":["legacy","vintage","commander","oathbreaker","duel"]},{"name":"Knight of Autumn","id":"c9cd7448-6f8b-4ce4-bde5-2c17271dcef7","ci":["G","W"],"commander":false,"legalities":["historic","gladiator","pioneer","explorer","modern","legacy","vintage","commander","oathbreaker","historicbrawl","duel"]},{"name":"Lightning Greaves","id":"1e5d9c01-f8db-43ef-bb50-f9e38e99f8d0","ci":[],"commander":false,"legalities":["modern","legacy","vintage","commander","oathbreaker","duel","predh"]},{"name":"Light Up the Stage","id":"351de611-2162-4d3e-9080-ad29fb300243","ci":["R"],"commander":false,"legalities":["historic","gladiator","pioneer","explorer","modern","legacy","vintage","commander","oathbreaker","historicbrawl","duel"]},{"name":"Lorcan, Warlock Collector","id":"5f6f90ae-340c-4eb7-b091-58db550be742","ci":["B"],"commander":true,"legalities":["legacy","vintage","commander","oathbreaker","duel"]},{"name":"Loyal Apprentice","id":"dab85ca8-1ce8-43df-a6a1-00fef6b1d1c0","ci":["R"],"commander":false,"legalities":["legacy","vintage","commander","oathbreaker","duel"]},{"name":"Lumbering Falls","id":"f7e9db98-3a2d-46d8-a07f-99d66a4d9f2f","ci":[],"commander":false,"legalities":["pioneer","modern","legacy","vintage","penny","commander","oathbreaker","duel"]},{"name":"Maddening Hex","id":"c8dd3a8d-5434-4405-8d17-e419a20f074a","ci":["R"],"commander":false,"legalities":["legacy","vintage","commander","oathbreaker"]},{"name":"Magmaquake","id":"8a8945b4-d2e1-4779-9c33-a8b062637fa6","ci":["R"],"commander":false,"legalities":["historic","gladiator","modern","legacy","vintage","penny","commander","oathbreaker","historicbrawl","duel"]},{"name":"Mantle of the Ancients","id":"867124fc-c8e4-4e0e-be41-b74a6bb34e86","ci":["W"],"commander":false,"legalities":["legacy","vintage","commander","oathbreaker","duel"]},{"name":"Marionette Master","id":"dd21a925-c76f-4c1d-b5b8-8d3352730e5f","ci":["B"],"commander":false,"legalities":["historic","gladiator","pioneer","explorer","modern","legacy","vintage","penny","commander","oathbreaker","historicbrawl","duel"]},{"name":"Masterwork of Ingenuity","id":"80b38b13-fc19-4ffc-8100-249f9eb8cca6","ci":[],"commander":false,"legalities":["legacy","vintage","commander","oathbreaker","duel"]},{"name":"Merfolk Looter","id":"6d740928-bf61-4420-a403-63097538b97d","ci":["U"],"commander":false,"legalities":["historic","gladiator","modern","legacy","pauper","vintage","penny","commander","oathbreaker","historicbrawl","paupercommander","duel","premodern","predh"]},{"name":"Meteor Golem","id":"e681f44b-17af-4d4b-a7fa-9445e6001a5f","ci":[],"commander":false,"legalities":["historic","gladiator","pioneer","explorer","modern","legacy","vintage","penny","commander","oathbreaker","historicbrawl","alchemy","duel"]},{"name":"Midnight Pathlighter","id":"8eb6f699-1b5d-412b-a697-ee94b7be07a6","ci":["U","W"],"commander":false,"legalities":["legacy","vintage","commander","oathbreaker","duel"]},{"name":"Mind Stone","id":"02a34135-0955-4045-9558-6e61338baaf0","ci":[],"commander":false,"legalities":["historic","gladiator","modern","legacy","pauper","vintage","commander","oathbreaker","historicbrawl","paupercommander","duel","premodern","predh"]},{"name":"Minn, Wily Illusionist","id":"4eec1d87-1007-44a1-a45d-0623816de681","ci":["U"],"commander":true,"legalities":["legacy","vintage","commander","oathbreaker","duel"]},{"name":"Mishra's Factory","id":"7c05c946-66c3-4785-90f9-ca0c606e036b","ci":[],"commander":false,"legalities":["modern","legacy","vintage","penny","commander","oathbreaker","duel","premodern","predh"]},{"name":"Moonsilver Spear","id":"a4ace878-6d15-4276-9bfb-2f23667c6d7e","ci":[],"commander":false,"legalities":["modern","legacy","vintage","penny","commander","oathbreaker","duel"]},{"name":"Mortuary Mire","id":"44082a22-406f-4050-b1be-de4f3e0fde5e","ci":[],"commander":false,"legalities":["pioneer","modern","legacy","pauper","vintage","penny","commander","oathbreaker","paupercommander","duel"]},{"name":"Mossfire Valley","id":"6e25404c-52ed-4553-a09a-a28a3b17c37f","ci":[],"commander":false,"legalities":["legacy","vintage","commander","oathbreaker","duel","premodern","predh"]},{"name":"Mosswort Bridge","id":"cbc74505-4d75-4bae-bf43-ec08731dfdd9","ci":[],"commander":false,"legalities":["modern","legacy","vintage","commander","oathbreaker","duel","predh"]},{"name":"Mulldrifter","id":"2fb5330d-5c1b-4caa-8d30-3ca8303ff611","ci":["U"],"commander":false,"legalities":["historic","gladiator","modern","legacy","pauper","vintage","commander","oathbreaker","historicbrawl","paupercommander","duel","predh"]},{"name":"Murder of Crows","id":"e8844c22-7ea4-4f2e-9066-e1df027e3fe3","ci":["U"],"commander":false,"legalities":["historic","gladiator","modern","legacy","vintage","penny","commander","oathbreaker","historicbrawl","duel"]},{"name":"Nature's Lore","id":"a2a64307-b0ab-4f28-ad37-47d8b4c8b882","ci":["G"],"commander":false,"legalities":["legacy","pauper","vintage","penny","commander","oathbreaker","paupercommander","duel","premodern","predh"]},{"name":"Necromantic Selection","id":"d3cec373-0a3f-4628-8706-b7c9c205f150","ci":["B"],"commander":false,"legalities":["legacy","vintage","commander","oathbreaker","duel"]},{"name":"Necrotic Sliver","id":"c0bf9c79-3a66-4c81-b7c7-9b31b4a67e32","ci":["B","W"],"commander":false,"legalities":["modern","legacy","vintage","penny","commander","oathbreaker","duel","predh"]},{"name":"Netherese Puzzle-Ward","id":"26bd3a70-3154-44a4-8705-1eac01cde8fd","ci":["U"],"commander":false,"legalities":["legacy","vintage","commander","oathbreaker","duel"]},{"name":"Neverwinter Hydra","id":"e57338ac-e794-41a0-8c3c-61df9c099cfb","ci":["G"],"commander":false,"legalities":["legacy","vintage","commander","oathbreaker","duel"]},{"name":"Nihiloor","id":"a652ac92-4e61-45ec-866e-baafefd355e5","ci":["B","U","W"],"commander":true,"legalities":["legacy","vintage","commander","oathbreaker","duel"]},{"name":"Nimbus Maze","id":"711dbdb1-7ec3-4fb4-8364-d34f5e143fd1","ci":[],"commander":false,"legalities":["modern","legacy","vintage","penny","commander","oathbreaker","duel","predh"]},{"name":"Obsessive Stitcher","id":"d319c8a2-ae7b-4077-8b11-97937979fed2","ci":["B","U"],"commander":false,"legalities":["historic","gladiator","pioneer","explorer","modern","legacy","vintage","penny","commander","oathbreaker","historicbrawl","duel"]},{"name":"Ogre Slumlord","id":"729f662d-e6b3-41ae-aed8-ef1c27b793d9","ci":["B"],"commander":false,"legalities":["historic","gladiator","pioneer","explorer","modern","legacy","vintage","penny","commander","oathbreaker","historicbrawl","duel"]},{"name":"Opportunistic Dragon","id":"cecf0f75-db79-4000-85cb-8344ac0f91c5","ci":["R"],"commander":false,"legalities":["historic","gladiator","pioneer","explorer","modern","legacy","vintage","penny","commander","oathbreaker","historicbrawl","duel"]},{"name":"Orazca Relic","id":"fd9e5b05-11b5-46fc-a1c8-484f41a0cee6","ci":[],"commander":false,"legalities":["historic","gladiator","pioneer","explorer","modern","legacy","pauper","vintage","penny","commander","oathbreaker","historicbrawl","paupercommander","duel"]},{"name":"Orzhov Basilica","id":"fc063704-f0d3-46b5-9340-f80d431ce5dc","ci":[],"commander":false,"legalities":["modern","legacy","pauper","vintage","penny","commander","oathbreaker","paupercommander","duel","predh"]},{"name":"Outpost Siege","id":"a8645f34-b830-4429-8fca-9458d1e3dccc","ci":["R"],"commander":false,"legalities":["pioneer","modern","legacy","vintage","penny","commander","oathbreaker","duel"]},{"name":"Paradise Druid","id":"187d5819-6a63-4e4f-98c4-18191c03f164","ci":["G"],"commander":false,"legalities":["historic","gladiator","pioneer","explorer","modern","legacy","vintage","commander","oathbreaker","historicbrawl","duel"]},{"name":"Path of Ancestry","id":"4ae7a4a1-0da6-44a9-b7e8-a28733580d0c","ci":[],"commander":false,"legalities":["legacy","pauper","vintage","penny","commander","oathbreaker","paupercommander","duel"]},{"name":"Phantasmal Image","id":"c1c080cf-a5e8-4d9d-af49-f78588971e87","ci":["U"],"commander":false,"legalities":["modern","legacy","vintage","penny","commander","oathbreaker","duel"]},{"name":"Phantom Steed","id":"64513f0a-067d-4b70-bb23-9ebe606bda1a","ci":["U"],"commander":false,"legalities":["legacy","vintage","commander","oathbreaker","duel"]},{"name":"Phthisis","id":"98b84356-fa97-4f61-bd84-e8efd7f46e38","ci":["B"],"commander":false,"legalities":["modern","legacy","vintage","penny","commander","oathbreaker","duel","predh"]},{"name":"Piper of the Swarm","id":"b4810704-beb8-499c-a921-26f672fd33b2","ci":["B"],"commander":false,"legalities":["historic","gladiator","pioneer","explorer","modern","legacy","vintage","penny","commander","oathbreaker","historicbrawl","duel"]},{"name":"Plaguecrafter","id":"5c03e00b-034d-4a26-9fc2-f25fc2dfc661","ci":["B"],"commander":false,"legalities":["historic","gladiator","pioneer","explorer","modern","legacy","vintage","commander","oathbreaker","historicbrawl","duel"]},{"name":"Pontiff of Blight","id":"c421b851-f61a-4db6-9063-d1d5289a7d78","ci":["B"],"commander":false,"legalities":["pioneer","modern","legacy","vintage","penny","commander","oathbreaker","duel"]},{"name":"Port Town","id":"e6a12a68-a88c-440d-a6ee-b235afbbbfb8","ci":[],"commander":false,"legalities":["historic","gladiator","pioneer","explorer","modern","legacy","vintage","commander","oathbreaker","historicbrawl","duel"]},{"name":"Prairie Stream","id":"9b724d9e-89d5-4e2f-9331-a60ee0d1893d","ci":[],"commander":false,"legalities":["pioneer","modern","legacy","vintage","commander","oathbreaker","duel"]},{"name":"Prognostic Sphinx","id":"acd9e468-093b-4c88-8bf6-041bee6a1ea2","ci":["U"],"commander":false,"legalities":["pioneer","modern","legacy","vintage","penny","commander","oathbreaker","duel"]},{"name":"Propaganda","id":"bc0331b2-7a5b-46f5-9698-f185431ca711","ci":["U"],"commander":false,"legalities":["legacy","vintage","commander","oathbreaker","duel","premodern","predh"]},{"name":"Prosper, Tome-Bound","id":"d743336e-d5c7-4053-a23d-92ec7581f74e","ci":["B","R"],"commander":true,"legalities":["historic","gladiator","legacy","vintage","commander","oathbreaker","historicbrawl","alchemy","duel"]},{"name":"Psychic Impetus","id":"5840b15e-0787-44ed-a2a7-29d0c8aa1cde","ci":["U"],"commander":false,"legalities":["legacy","pauper","vintage","commander","oathbreaker","paupercommander","duel"]},{"name":"Puresteel Paladin","id":"6dfd52a8-14c0-4e53-862e-01da4d7823e2","ci":["W"],"commander":false,"legalities":["modern","legacy","vintage","commander","oathbreaker","duel","predh"]},{"name":"Radiant Solar","id":"fa0e443a-c479-40ab-9702-8beca3e5ab95","ci":["W"],"commander":false,"legalities":["legacy","vintage","commander","oathbreaker","duel"]},{"name":"Rakdos Carnarium","id":"b18103c9-b92f-4f65-93ba-d18d3fd5b557","ci":[],"commander":false,"legalities":["modern","legacy","pauper","vintage","commander","oathbreaker","paupercommander","duel","predh"]},{"name":"Rakdos Charm","id":"3632fbff-c3cc-4f6f-b15d-c7ca3cb77a7c","ci":["B","R"],"commander":false,"legalities":["pioneer","modern","legacy","vintage","penny","commander","oathbreaker","duel"]},{"name":"Rakdos Signet","id":"0bc3c10a-c3be-4e46-9871-282dad8bc7a4","ci":[],"commander":false,"legalities":["modern","legacy","pauper","vintage","penny","commander","oathbreaker","paupercommander","duel","predh"]},{"name":"Rampant Growth","id":"18992876-740a-4c30-b2fd-b6a5afd467b4","ci":["G"],"commander":false,"legalities":["modern","legacy","pauper","vintage","penny","commander","oathbreaker","paupercommander","duel","premodern","predh"]},{"name":"Rancor","id":"26ddcdcc-28eb-43ce-b912-499c735491b8","ci":["G"],"commander":false,"legalities":["modern","legacy","pauper","vintage","commander","oathbreaker","paupercommander","duel","premodern","predh"]},{"name":"Realm-Cloaked Giant // Cast Off","id":"d6fc6ed9-740a-4726-8f2c-5d662636f687","ci":["W"],"legalities":["historic","gladiator","pioneer","explorer","modern","legacy","vintage","commander","oathbreaker","historicbrawl","duel"]},{"name":"Reassembling Skeleton","id":"dd82846e-f119-4b27-a795-7b1ceebab4b0","ci":["B"],"commander":false,"legalities":["historic","gladiator","pioneer","explorer","modern","legacy","vintage","penny","commander","oathbreaker","historicbrawl","duel","predh"]},{"name":"Reckless Endeavor","id":"ba98a4bd-e217-4dba-aee9-315b4f843cdf","ci":["R"],"commander":false,"legalities":["legacy","vintage","commander","oathbreaker","duel"]},{"name":"Return of the Wildspeaker","id":"2b809f30-5ea5-4b09-92ee-13cb4404b095","ci":["G"],"commander":false,"legalities":["historic","gladiator","pioneer","explorer","modern","legacy","vintage","commander","oathbreaker","historicbrawl","duel"]},{"name":"Return to Nature","id":"4bebe9fa-1697-48fc-9044-cd58a3eab836","ci":["G"],"commander":false,"legalities":["standard","future","historic","gladiator","pioneer","explorer","modern","legacy","pauper","vintage","penny","commander","oathbreaker","brawl","historicbrawl","alchemy","paupercommander","duel"]},{"name":"Revivify","id":"6d21fb27-e821-4ce1-8f34-fc5d6c69d779","ci":["W"],"commander":false,"legalities":["legacy","vintage","commander","oathbreaker","duel"]},{"name":"Ride the Avalanche","id":"9e32eded-f9a2-4512-b82e-64445f8df8a3","ci":["G","U"],"commander":false,"legalities":["legacy","vintage","commander","oathbreaker","duel"]},{"name":"Rile","id":"89f51602-0ab8-4acd-9734-16ef05953970","ci":["R"],"commander":false,"legalities":["historic","gladiator","pioneer","explorer","modern","legacy","pauper","vintage","penny","commander","oathbreaker","historicbrawl","paupercommander","duel"]},{"name":"Rishkar's Expertise","id":"525e605c-5579-4524-9d7b-f7edac4e4d96","ci":["G"],"commander":false,"legalities":["historic","gladiator","pioneer","explorer","modern","legacy","vintage","penny","commander","oathbreaker","historicbrawl","duel"]},{"name":"Riverwise Augur","id":"cc1c3923-aeb0-4f53-a210-10542534b121","ci":["U"],"commander":false,"legalities":["historic","gladiator","pioneer","explorer","modern","legacy","vintage","penny","commander","oathbreaker","historicbrawl","duel"]},{"name":"Robe of Stars","id":"b2992175-5499-4a83-9ff2-03c7c34819c3","ci":["W"],"commander":false,"legalities":["legacy","vintage","commander","oathbreaker","duel"]},{"name":"Rod of Absorption","id":"59e9e244-bb8e-4346-b06b-4af987473442","ci":["U"],"commander":false,"legalities":["legacy","vintage","commander","oathbreaker","duel"]},{"name":"Ronom Unicorn","id":"b3275ed0-30b2-4d30-aa03-0dbda913f530","ci":["W"],"commander":false,"legalities":["historic","gladiator","modern","legacy","pauper","vintage","penny","commander","oathbreaker","historicbrawl","paupercommander","duel","predh"]},{"name":"Savage Ventmaw","id":"1779ab27-f0fc-4dc7-9a0f-01cd70776a31","ci":["G","R"],"commander":false,"legalities":["pioneer","modern","legacy","vintage","commander","oathbreaker","duel"]},{"name":"Scourge of Valkas","id":"e6bd7225-b39f-4b3b-8c36-dbc2c09f6e50","ci":["R"],"commander":false,"legalities":["pioneer","modern","legacy","vintage","commander","oathbreaker","duel"]},{"name":"Seaside Citadel","id":"4f35d808-51c7-42b1-bbd5-1cd452432cd6","ci":[],"commander":false,"legalities":["modern","legacy","vintage","penny","commander","oathbreaker","duel","predh"]},{"name":"Sefris of the Hidden Ways","id":"d30255f6-e058-476a-b377-2ee4c9178ed1","ci":["B","U","W"],"commander":true,"legalities":["legacy","vintage","commander","oathbreaker","duel"]},{"name":"Serum Visions","id":"8405a6c8-1dfb-4ac5-b44c-bce9e4bcc38c","ci":["U"],"commander":false,"legalities":["modern","legacy","pauper","vintage","commander","oathbreaker","paupercommander","duel","predh"]},{"name":"Shadowblood Ridge","id":"74c0016a-6761-4764-bf4a-ecde26061a90","ci":[],"commander":false,"legalities":["legacy","vintage","commander","oathbreaker","duel","premodern","predh"]},{"name":"Shamanic Revelation","id":"22d99567-8b8a-45cf-85f9-233e97256194","ci":["G"],"commander":false,"legalities":["pioneer","modern","legacy","vintage","penny","commander","oathbreaker","duel"]},{"name":"Share the Spoils","id":"5e35d719-8766-47dc-8c0d-8e2b37b907a8","ci":["R"],"commander":false,"legalities":["legacy","vintage","commander","oathbreaker","duel"]},{"name":"Shielding Plax","id":"81e632d8-ee9c-4635-9654-4d6405cb0bf2","ci":["G","U"],"commander":false,"legalities":["modern","legacy","pauper","vintage","penny","commander","oathbreaker","paupercommander","duel","predh"]},{"name":"Shiny Impetus","id":"82bf32e5-5841-448b-b5e7-cba87a726295","ci":["R"],"commander":false,"legalities":["legacy","pauper","vintage","commander","oathbreaker","paupercommander","duel"]},{"name":"Shivan Hellkite","id":"d33cfe2d-150d-4ab7-990a-c8b0b6ff4d37","ci":["R"],"commander":false,"legalities":["modern","legacy","vintage","penny","commander","oathbreaker","duel","premodern","predh"]},{"name":"Shriekmaw","id":"18e3ebe5-9350-4781-a30d-4fcad034e7a9","ci":["B"],"commander":false,"legalities":["modern","legacy","vintage","penny","commander","oathbreaker","duel","predh"]},{"name":"Simic Growth Chamber","id":"c8f84235-758a-41b9-8b6c-185b64c00ca2","ci":[],"commander":false,"legalities":["modern","legacy","pauper","vintage","commander","oathbreaker","paupercommander","duel","predh"]},{"name":"Skycloud Expanse","id":"5510e165-f632-47e7-84c6-b5346e46ac9a","ci":[],"commander":false,"legalities":["legacy","vintage","commander","oathbreaker","duel","premodern","predh"]},{"name":"Skyline Despot","id":"fabdbd03-6f1e-4ada-ad90-5c72d7e305b6","ci":["R"],"commander":false,"legalities":["legacy","vintage","commander","oathbreaker","duel"]},{"name":"Skyship Stalker","id":"6ea1dbf2-f3fb-40c4-86df-cd2511d27088","ci":["R"],"commander":false,"legalities":["historic","gladiator","pioneer","explorer","modern","legacy","vintage","penny","commander","oathbreaker","historicbrawl","duel"]},{"name":"Smoldering Marsh","id":"02d90054-65da-4562-bfe7-48c381757b30","ci":[],"commander":false,"legalities":["pioneer","modern","legacy","vintage","commander","oathbreaker","duel"]},{"name":"Solemn Simulacrum","id":"71ec1e1d-8c7b-40e9-b916-440f8acf3ea5","ci":[],"commander":false,"legalities":["historic","gladiator","pioneer","explorer","modern","legacy","vintage","penny","commander","oathbreaker","historicbrawl","duel","predh"]},{"name":"Sol Ring","id":"2c52c96d-e20f-4025-b759-674b36cf0db3","ci":[],"commander":false,"legalities":["commander","predh"]},{"name":"Song of Inspiration","id":"a231a41f-1609-420f-9a9b-3c8358591da1","ci":["G"],"commander":false,"legalities":["legacy","vintage","commander","oathbreaker","duel"]},{"name":"Spinerock Knoll","id":"6bfb3dac-94d7-4b94-9a9e-6392d5ce5bf2","ci":[],"commander":false,"legalities":["modern","legacy","vintage","penny","commander","oathbreaker","duel","predh"]},{"name":"Spit Flame","id":"b5bf8493-2592-48e0-9c45-bb7974c30aed","ci":["R"],"commander":false,"legalities":["historic","gladiator","pioneer","explorer","modern","legacy","vintage","penny","commander","oathbreaker","historicbrawl","duel"]},{"name":"Sram, Senior Edificer","id":"4c9b0adf-d281-4729-a3b7-269665fe4be1","ci":["W"],"commander":true,"legalities":["historic","gladiator","pioneer","explorer","modern","legacy","vintage","commander","oathbreaker","historicbrawl","duel"]},{"name":"Storvald, Frost Giant Jarl","id":"8a5a45a7-d159-4821-8916-697b92fb80bf","ci":["G","U","W"],"commander":true,"legalities":["legacy","vintage","commander","oathbreaker","duel"]},{"name":"Sunblast Angel","id":"680f7d5c-d518-4ebb-92d5-e835cd9eafe0","ci":["W"],"commander":false,"legalities":["modern","legacy","vintage","penny","commander","oathbreaker","duel","predh"]},{"name":"Sungrass Prairie","id":"6ed96237-ef35-4665-881b-868634161717","ci":[],"commander":false,"legalities":["legacy","vintage","commander","oathbreaker","duel","premodern","predh"]},{"name":"Sunken Hollow","id":"29982d94-9824-4371-95f6-d5050b1895ce","ci":[],"commander":false,"legalities":["pioneer","modern","legacy","vintage","commander","oathbreaker","duel"]},{"name":"Sun Titan","id":"e0f6b7d1-75ea-4153-bbf1-85ed5041fe67","ci":["W"],"commander":false,"legalities":["modern","legacy","vintage","commander","oathbreaker","duel","predh"]},{"name":"Swiftfoot Boots","id":"bc89db46-0df6-4ce1-b162-233f5fe1b554","ci":[],"commander":false,"legalities":["historic","gladiator","modern","legacy","vintage","commander","oathbreaker","historicbrawl","duel"]},{"name":"Sword of Hours","id":"eaedf482-9f2c-497a-bf1c-bebb4168c52f","ci":[],"commander":false,"legalities":["legacy","vintage","commander","oathbreaker","duel"]},{"name":"Sword of the Animist","id":"3bfa6b8c-6e4b-42fa-9f6c-40c95e162b9a","ci":[],"commander":false,"legalities":["pioneer","modern","legacy","vintage","commander","oathbreaker","duel"]},{"name":"Swords to Plowshares","id":"be45567a-ca1d-4e3a-a630-ddf4fbd97bc6","ci":["W"],"commander":false,"legalities":["gladiator","legacy","vintage","commander","oathbreaker","historicbrawl","duel","premodern","predh"]},{"name":"Tainted Peak","id":"e5dd195d-6f81-4ff8-b950-455ab462ec7d","ci":[],"commander":false,"legalities":["legacy","vintage","commander","oathbreaker","duel","premodern","predh"]},{"name":"Talisman of Indulgence","id":"fa6c62c7-8fd4-46f1-a7f4-fc6e74d34b35","ci":[],"commander":false,"legalities":["modern","legacy","vintage","commander","oathbreaker","duel","predh"]},{"name":"Taurean Mauler","id":"ed75b280-c7c5-404f-bbad-c19dff3e6975","ci":["R"],"commander":false,"legalities":["modern","legacy","vintage","penny","commander","oathbreaker","duel","predh"]},{"name":"Tectonic Giant","id":"8eb94800-1d87-4140-91cb-ba9ca49572ad","ci":["R"],"commander":false,"legalities":["historic","gladiator","pioneer","explorer","modern","legacy","vintage","penny","commander","oathbreaker","historicbrawl","duel"]},{"name":"Terminate","id":"4c942af8-e5c1-47e0-a662-d9ef531f0dad","ci":["B","R"],"commander":false,"legalities":["modern","legacy","pauper","vintage","commander","oathbreaker","paupercommander","duel","premodern","predh"]},{"name":"Terramorphic Expanse","id":"08ac4e43-4e16-46a2-96f5-58d5550984c4","ci":[],"commander":false,"legalities":["standard","future","historic","gladiator","pioneer","explorer","modern","legacy","pauper","vintage","penny","commander","oathbreaker","brawl","historicbrawl","alchemy","paupercommander","duel","predh"]},{"name":"Terror of Mount Velus","id":"7bed9dbb-6a1d-411f-9139-3dc20258020a","ci":["R"],"commander":false,"legalities":["historic","gladiator","pioneer","explorer","modern","legacy","vintage","commander","oathbreaker","historicbrawl","duel"]},{"name":"Theater of Horrors","id":"72651e82-ab11-4ec7-812a-8cff8d7e7a2e","ci":["B","R"],"commander":false,"legalities":["historic","gladiator","pioneer","explorer","modern","legacy","vintage","penny","commander","oathbreaker","historicbrawl","duel"]},{"name":"Thorough Investigation","id":"a40e6034-aa05-4542-ac12-78e6a76d86e9","ci":["W"],"commander":false,"legalities":["legacy","vintage","commander","oathbreaker","duel"]},{"name":"Thriving Grove","id":"0de19659-5b50-4917-b8dd-e030aa72868d","ci":[],"commander":false,"legalities":["historic","gladiator","legacy","pauper","vintage","commander","oathbreaker","historicbrawl","paupercommander","duel"]},{"name":"Thriving Heath","id":"5677c5a9-e63f-4d13-91dc-beeb6875f675","ci":[],"commander":false,"legalities":["historic","gladiator","legacy","pauper","vintage","commander","oathbreaker","historicbrawl","paupercommander","duel"]},{"name":"Thriving Isle","id":"d50646a7-f5a7-4106-b660-98ee4bd4d93b","ci":[],"commander":false,"legalities":["historic","gladiator","legacy","pauper","vintage","commander","oathbreaker","historicbrawl","paupercommander","duel"]},{"name":"Thriving Moor","id":"7faa30a1-ca8c-4462-90ea-8e935cad0a53","ci":[],"commander":false,"legalities":["historic","gladiator","legacy","pauper","vintage","commander","oathbreaker","historicbrawl","paupercommander","duel"]},{"name":"Throes of Chaos","id":"d27a6cfc-9864-4081-93ab-9dfb254c1cd0","ci":["R"],"commander":false,"legalities":["historic","gladiator","modern","legacy","vintage","penny","commander","oathbreaker","historicbrawl","duel"]},{"name":"Thunderbreak Regent","id":"fbc60f6f-da15-4109-acf6-34ac9e4de9f9","ci":["R"],"commander":false,"legalities":["historic","gladiator","pioneer","explorer","modern","legacy","vintage","penny","commander","oathbreaker","historicbrawl","duel"]},{"name":"Unburial Rites","id":"56b386bf-4678-43ab-80a2-a79e3c50bac1","ci":["B"],"commander":false,"legalities":["historic","gladiator","modern","legacy","vintage","penny","commander","oathbreaker","historicbrawl","duel"]},{"name":"Underdark Rift","id":"da7b5c5b-fba1-4993-9779-bef96bcb0064","ci":[],"commander":false,"legalities":["legacy","vintage","commander","oathbreaker","duel"]},{"name":"Unstable Obelisk","id":"96f90a63-fe42-4bd5-8126-dd1f48397d4e","ci":[],"commander":false,"legalities":["historic","gladiator","legacy","pauper","vintage","commander","oathbreaker","historicbrawl","paupercommander","duel"]},{"name":"Utopia Sprawl","id":"29b4050e-8b73-4f16-85e4-ec2a8faacf48","ci":["G"],"commander":false,"legalities":["modern","legacy","pauper","vintage","commander","oathbreaker","paupercommander","duel","predh"]},{"name":"Utter End","id":"0abda7f5-89c2-43ad-bcc9-8b802881c373","ci":["B","W"],"commander":false,"legalities":["pioneer","modern","legacy","vintage","penny","commander","oathbreaker","duel"]},{"name":"Valiant Endeavor","id":"0445def0-8921-4579-912f-035d9fbce3c0","ci":["W"],"commander":false,"legalities":["legacy","vintage","commander","oathbreaker","duel"]},{"name":"Valorous Stance","id":"ba539280-c642-4789-b91a-d1c08a5ca657","ci":["W"],"commander":false,"legalities":["standard","future","historic","gladiator","pioneer","explorer","modern","legacy","vintage","commander","oathbreaker","brawl","historicbrawl","alchemy","duel"]},{"name":"Vandalblast","id":"6239c8c9-113f-410b-8894-94d7287ac8d4","ci":["R"],"commander":false,"legalities":["pioneer","modern","legacy","vintage","penny","commander","oathbreaker","duel"]},{"name":"Vanish into Memory","id":"60dd9f6e-c848-4670-8de1-06f328ea7f71","ci":["U","W"],"commander":false,"legalities":["modern","legacy","vintage","penny","commander","oathbreaker","duel","predh"]},{"name":"Vengeful Ancestor","id":"badc03ae-b04a-4612-a95f-27865d2d09df","ci":["R"],"commander":false,"legalities":["legacy","vintage","commander","oathbreaker","duel"]},{"name":"Verdant Embrace","id":"57233676-f03f-4739-a1fb-8fed7e6c649f","ci":["G"],"commander":false,"legalities":["historic","gladiator","modern","legacy","vintage","penny","commander","oathbreaker","historicbrawl","duel","predh"]},{"name":"Victimize","id":"1303644e-d406-4136-8524-9d99f0b318ac","ci":["B"],"commander":false,"legalities":["legacy","vintage","commander","oathbreaker","duel","premodern","predh"]},{"name":"Viridian Longbow","id":"f4607634-6206-4c6c-b389-abcbfe969b65","ci":[],"commander":false,"legalities":["modern","legacy","pauper","vintage","commander","oathbreaker","paupercommander","duel","predh"]},{"name":"Vitu-Ghazi, the City-Tree","id":"33145080-077e-4231-96ca-e8b1852b6380","ci":[],"commander":false,"legalities":["modern","legacy","vintage","penny","commander","oathbreaker","duel","predh"]},{"name":"Vrondiss, Rage of Ancients","id":"683ca7f0-e9df-459b-a8e3-cf80b39c732d","ci":["G","R"],"commander":true,"legalities":["legacy","vintage","commander","oathbreaker","duel"]},{"name":"Wall of Omens","id":"0db4b34f-2d60-4ff3-8ef7-9cedb9b71cdc","ci":["W"],"commander":false,"legalities":["modern","legacy","vintage","commander","oathbreaker","duel","predh"]},{"name":"Wand of Orcus","id":"510af4b7-289a-4de7-9a22-00fe1e8aaabf","ci":["B"],"commander":false,"legalities":["historic","gladiator","legacy","vintage","commander","oathbreaker","historicbrawl","alchemy","duel"]},{"name":"Warstorm Surge","id":"596ebc25-b55c-45e7-8aba-97f4ba0c766a","ci":["R"],"commander":false,"legalities":["modern","legacy","vintage","penny","commander","oathbreaker","duel"]},{"name":"Wayfarer's Bauble","id":"32a52319-e4a5-42a9-b9c5-35df42b46fd9","ci":[],"commander":false,"legalities":["modern","legacy","pauper","vintage","commander","oathbreaker","paupercommander","duel","predh"]},{"name":"Wild Endeavor","id":"349d0255-52b9-4998-ad4b-909a593c3071","ci":["G"],"commander":false,"legalities":["legacy","vintage","commander","oathbreaker","duel"]},{"name":"Wild Growth","id":"61efbd57-7e56-4087-beba-18d8445db7dd","ci":["G"],"commander":false,"legalities":["legacy","pauper","vintage","commander","oathbreaker","paupercommander","duel","premodern","predh"]},{"name":"Wild-Magic Sorcerer","id":"a48df69d-ef3d-46b1-8811-b6a1be777cdc","ci":["R"],"commander":false,"legalities":["legacy","vintage","commander","oathbreaker","duel"]},{"name":"Winds of Rath","id":"91ee4ff1-8b18-401b-9914-b7bb2851591b","ci":["W"],"commander":false,"legalities":["legacy","vintage","penny","commander","oathbreaker","duel","premodern","predh"]},{"name":"Winged Boots","id":"d1aa5f8a-e965-45db-8957-f5c3fe3f2ebb","ci":["U"],"commander":false,"legalities":["legacy","vintage","commander","oathbreaker","duel"]},{"name":"Wulfgar of Icewind Dale","id":"80665af6-fd66-4684-94ec-1f04eb898c2a","ci":["G","R"],"commander":true,"legalities":["legacy","vintage","commander","oathbreaker","duel"]},{"name":"Zhalfirin Void","id":"d481d871-d1e3-439b-bfd5-5b2212f9b0c8","ci":[],"commander":false,"legalities":["historic","gladiator","pioneer","explorer","modern","legacy","vintage","penny","commander","oathbreaker","historicbrawl","duel"]}]