[{"name":"Cathartic Reunion","id":"8c1a02f9-3ce7-46e9-8d0e-0d491bb13012","type":"Sorcery","ci":["R"],"commander":false,"legalities":["historic","gladiator","pioneer","explorer","modern","legacy","pauper","vintage","penny","commander","oathbreaker","historicbrawl","paupercommander","duel"]},{"name":"Chandra, Torch of Defiance","id":"c7bbb911-9de2-455d-9677-e1004db65dbd","type":"Legendary Planeswalker — Chandra","ci":["R"],"commander":false,"legalities":["historic","gladiator","pioneer","explorer","modern","legacy","vintage","commander","oathbreaker","historicbrawl","duel"]},{"name":"Fiery Confluence","id":"4c454a20-8ec8-41d9-b9c3-acaa510d050b","type":"Sorcery","ci":["R"],"commander":false,"legalities":["legacy","vintage","commander","oathbreaker","duel"]},{"name":"Past in Flames","id":"d1bf32c4-4f0d-4c50-b6e5-2e6a4456bd1d","type":"Sorcery","ci":["R"],"commander":false,"legalities":["historic","gladiator","modern","legacy","vintage","commander","oathbreaker","historicbrawl","duel"]},{"name":"Pyroblast","id":"93c460dc-cef2-4345-b9b8-a774307ba2d6","type":"Instant","ci":["R"],"commander":false,"legalities":["legacy","pauper","vintage","commander","oathbreaker","paupercommander","duel","premodern","predh"]},{"name":"Pyromancer Ascension","id":"aeffd6f6-0fee-4afc-9256-04099d9d41aa","type":"Enchantment","ci":["R"],"commander":false,"legalities":["modern","legacy","vintage","penny","commander","oathbreaker","duel","predh"]},{"name":"Rite of Flame","id":"10548126-2bac-435d-b7ee-cbfea97a40ea","type":"Sorcery","ci":["R"],"commander":false,"legalities":["legacy","pauper","vintage","commander","oathbreaker","paupercommander","duel","predh"]},{"name":"Young Pyromancer","id":"2dd80b9f-5c35-438b-ba52-da0e3e8ff781","type":"Creature — Human Shaman","ci":["R"],"commander":false,"legalities":["historic","gladiator","pioneer","explorer","modern","legacy","vintage","commander","oathbreaker","historicbrawl","duel"]}]